{
  "accentColor": "{{appsmith.theme.colors.primaryColor}}",
  "additionalStaticProps": [
    "level",
    "levelData",
    "prefixMetaWidgetId",
    "metaWidgetId"
  ],
  "animateLoading": true,
  "backgroundColor": "{{appsmith.theme.colors.backgroundColor}}",
  "borderRadius": "{{appsmith.theme.borderRadius.appBorderRadius}}",
  "bottomRow": 29,
  "boxShadow": "{{appsmith.theme.boxShadow.appBoxShadow}}",
  "children": [
    {
      "borderRadius": "{{appsmith.theme.borderRadius.appBorderRadius}}",
      "bottomRow": 210,
      "boxShadow": "{{appsmith.theme.boxShadow.appBoxShadow}}",
      "canExtend": false,
      "containerStyle": "none",
      "detachFromLayout": true,
      "dropDisabled": true,
      "dynamicBindingPathList": [
        {
          "key": "borderRadius"
        },
        {
          "key": "boxShadow"
        }
      ],
      "dynamicHeight": "AUTO_HEIGHT",
      "flexLayers": [],
      "isLoading": false,
      "isVisible": true,
      "key": "f94ewr0om3",
      "leftColumn": 0,
      "maxDynamicHeight": 9000,
      "minDynamicHeight": 4,
      "minHeight": 400,
      "minWidth": 450,
      "mobileBottomRow": 400,
      "mobileLeftColumn": 0,
      "mobileRightColumn": 297.30127716064453,
      "mobileTopRow": 0,
      "needsErrorInfo": false,
      "noPad": true,
      "openParentPropertyPane": true,
      "parentColumnSpace": 1,
      "parentId": "5hp8i2pfns",
      "parentRowSpace": 1,
      "renderMode": "CANVAS",
      "responsiveBehavior": "fill",
      "rightColumn": 297.30127716064453,
      "topRow": 0,
      "type": "CANVAS_WIDGET",
      "version": 1,
      "widgetId": "vh11ozwxf7",
      "widgetName": "Canvas15"
    }
  ],
  "currentItemsView": "{{[]}}",
  "dynamicBindingPathList": [
    {
      "key": "currentItemsView"
    },
    {
      "key": "selectedItemView"
    },
    {
      "key": "triggeredItemView"
    },
    {
      "key": "primaryKeys"
    },
    {
      "key": "accentColor"
    },
    {
      "key": "borderRadius"
    },
    {
      "key": "boxShadow"
    },
    {
      "key": "listData"
    },
    {
      "key": "backgroundColor"
    }
  ],
  "dynamicTriggerPathList": [],
  "enhancements": true,
  "flexVerticalAlignment": "start",
  "gridType": "vertical",
  "hasMetaWidgets": true,
  "isCanvas": true,
  "isLoading": false,
  "isVisible": true,
  "itemBackgroundColor": "#FFFFFF",
  "itemSpacing": 8,
  "key": "umt683rznu",
  "leftColumn": 11,
  "listData": "{{getTestResults.data[0].concerns}}",
  "mainCanvasId": "vh11ozwxf7",
  "mainContainerId": "93ndkxzmrk",
  "minWidth": 450,
  "mobileBottomRow": 56,
  "mobileLeftColumn": 11,
  "mobileRightColumn": 35,
  "mobileTopRow": 16,
  "needsErrorInfo": false,
  "originalBottomRow": 29,
  "originalTopRow": 8,
  "pageSize": 3,
  "parentColumnSpace": 12.387553215026855,
  "parentId": "cc097kjn6x",
  "parentRowSpace": 10,
  "primaryKeys": "{{List4.listData.map((currentItem, currentIndex) => currentItem[\"concernId\"] )}}",
  "renderMode": "CANVAS",
  "requiresFlatWidgetChildren": true,
  "responsiveBehavior": "fill",
  "rightColumn": 35,
  "selectedItemView": "{{{}}}",
  "templateHeight": 160,
  "topRow": 8,
  "triggeredItemView": "{{{}}}",
  "type": "LIST_WIDGET_V2",
  "widgetId": "5hp8i2pfns",
  "widgetName": "List4"
}