{
  "animateLoading": true,
  "borderRadius": "{{appsmith.theme.borderRadius.appBorderRadius}}",
  "bottomRow": 90,
  "dynamicBindingPathList": [
    {
      "key": "truncateButtonColor"
    },
    {
      "key": "fontFamily"
    },
    {
      "key": "borderRadius"
    }
  ],
  "dynamicHeight": "AUTO_HEIGHT",
  "dynamicTriggerPathList": [],
  "fontFamily": "{{appsmith.theme.fontFamily.appFont}}",
  "fontSize": "0.875rem",
  "fontStyle": "",
  "isLoading": false,
  "isVisible": true,
  "key": "snvpb9xecb",
  "leftColumn": 21,
  "maxDynamicHeight": 9000,
  "minDynamicHeight": 4,
  "minWidth": 450,
  "mobileBottomRow": 6,
  "mobileLeftColumn": 5,
  "mobileRightColumn": 21,
  "mobileTopRow": 2,
  "needsErrorInfo": false,
  "originalBottomRow": 89,
  "originalTopRow": 83,
  "overflow": "NONE",
  "parentColumnSpace": 9.0390625,
  "parentId": "k56vv90gai",
  "parentRowSpace": 10,
  "renderMode": "CANVAS",
  "responsiveBehavior": "fill",
  "rightColumn": 61,
  "shouldTruncate": false,
  "text": "Our misson at SkinMatch is to find the best skincare product for you! By identifying your needs and concerns and recommending products by ingredients that help you glow!",
  "textAlign": "LEFT",
  "textColor": "#5f7491",
  "topRow": 84,
  "truncateButtonColor": "{{appsmith.theme.colors.primaryColor}}",
  "type": "TEXT_WIDGET",
  "version": 1,
  "widgetId": "2okhgojuge",
  "widgetName": "Text7CopyCopyCopy"
}