{
  "animateLoading": true,
  "borderRadius": "{{appsmith.theme.borderRadius.appBorderRadius}}",
  "bottomRow": 10,
  "boxShadow": "none",
  "buttonColor": "{{appsmith.store.buttonClicked ? '#d4d4d8' : '#ef4444'}}",
  "buttonVariant": "TERTIARY",
  "dynamicBindingPathList": [
    {
      "key": "borderRadius"
    },
    {
      "key": "buttonColor"
    }
  ],
  "dynamicPropertyPathList": [
    {
      "key": "isVisible"
    },
    {
      "key": "buttonColor"
    }
  ],
  "dynamicTriggerPathList": [
    {
      "key": "onClick"
    }
  ],
  "iconName": "heart",
  "isDisabled": false,
  "isLoading": false,
  "isVisible": "true",
  "key": "wzr6nn0ks7",
  "leftColumn": 5,
  "minWidth": 50,
  "mobileBottomRow": 4,
  "mobileLeftColumn": 60,
  "mobileRightColumn": 64,
  "mobileTopRow": 0,
  "needsErrorInfo": false,
  "onClick": "{{toggleFavs.run().then(() => {\n  getFavs.run();\n  storeValue('favs', getFavs.data);\n});\nstoreValue('favColour', 'false');}}",
  "parentColumnSpace": 12.580078125,
  "parentId": "y4hg2xh4fe",
  "parentRowSpace": 10,
  "renderMode": "CANVAS",
  "responsiveBehavior": "hug",
  "rightColumn": 9,
  "topRow": 6,
  "type": "ICON_BUTTON_WIDGET",
  "version": 1,
  "widgetId": "ocncrvye05",
  "widgetName": "IconButton6"
}